jobcrawler/__init__.py
jobcrawler/scraper.py
jobcrawler/scraper/async_scraper.py
jobcrawler/scraper/sync_scraper.py
jobcrawler/utils/greenhouse.py
jobcrawler/utils/lever.py
jobcrawler-0.1.5.dist-info/licenses/LICENSE
jobcrawler-0.1.5.dist-info/METADATA
jobcrawler-0.1.5.dist-info/WHEEL
jobcrawler-0.1.5.dist-info/top_level.txt
jobcrawler-0.1.5.dist-info/RECORD
