Metadata-Version: 2.4
Name: jobcrawler
Version: 0.1.5
Summary: Python project to automate extracting job information directly from ATS
Author-email: Eric Yang <notmyemail@notmyemail.com>
License: MIT
Keywords: jobs,crawler,scraping,automation
Classifier: Programming Language :: Python :: 3
Classifier: License :: OSI Approved :: MIT License
Classifier: Operating System :: OS Independent
Requires-Python: >=3.10
License-File: LICENSE
Dynamic: license-file
